README.rst
setup.py
sayhello/__init__.py
sayhello/say.py
sayhello.egg-info/PKG-INFO
sayhello.egg-info/SOURCES.txt
sayhello.egg-info/dependency_links.txt
sayhello.egg-info/entry_points.txt
sayhello.egg-info/top_level.txt