Metadata-Version: 1.1
Name: sayhello
Version: 0.1.4
Summary: say text on the command-line
Home-page: https://github.com/catplant/say-hello
Author: catplanet
Author-email: catplanet@qq.com
License: MIT
Keywords: say command text
Platform: UNKNOWN
Classifier: Development Status :: 3 - Alpha
Classifier: License :: OSI Approved :: MIT License
Classifier: Natural Language :: Chinese (Simplified)
Classifier: Programming Language :: Python :: 2.7
Classifier: Programming Language :: Python :: 3
Classifier: Programming Language :: Python :: 3.3
Classifier: Programming Language :: Python :: 3.4
Classifier: Programming Language :: Python :: 3.5
